PTAfast/__init__.py
PTAfast/hellingsdowns.py
PTAfast/scalar.py
PTAfast/tensor.py
PTAfast/vector.py
PTAfast-0.0.1.dist-info/LICENSE
PTAfast-0.0.1.dist-info/METADATA
PTAfast-0.0.1.dist-info/WHEEL
PTAfast-0.0.1.dist-info/top_level.txt
PTAfast-0.0.1.dist-info/RECORD
